iqm/pulse/__init__.py
iqm/pulse/base_utils.py
iqm/pulse/builder.py
iqm/pulse/circuit_operations.py
iqm/pulse/gate_implementation.py
iqm/pulse/py.typed
iqm/pulse/quantum_ops.py
iqm/pulse/scheduler.py
iqm/pulse/timebox.py
iqm/pulse/utils.py
iqm/pulse/validation.py
iqm/pulse/gates/__init__.py
iqm/pulse/gates/barrier.py
iqm/pulse/gates/conditional.py
iqm/pulse/gates/cz.py
iqm/pulse/gates/default_gates.py
iqm/pulse/gates/delay.py
iqm/pulse/gates/enums.py
iqm/pulse/gates/flux_multiplexer.py
iqm/pulse/gates/measure.py
iqm/pulse/gates/move.py
iqm/pulse/gates/prx.py
iqm/pulse/gates/reset.py
iqm/pulse/gates/rz.py
iqm/pulse/gates/sx.py
iqm/pulse/gates/u.py
iqm/pulse/playlist/__init__.py
iqm/pulse/playlist/channel.py
iqm/pulse/playlist/fast_drag.py
iqm/pulse/playlist/hd_drag.py
iqm/pulse/playlist/instructions.py
iqm/pulse/playlist/playlist.py
iqm/pulse/playlist/schedule.py
iqm/pulse/playlist/waveforms.py
iqm/pulse/playlist/visualisation/__init__.py
iqm/pulse/playlist/visualisation/base.py
iqm/pulse/playlist/visualisation/templates/playlist_inspection.jinja2
iqm/pulse/playlist/visualisation/templates/static/logo.png
iqm/pulse/playlist/visualisation/templates/static/moment.min.js
iqm/pulse/playlist/visualisation/templates/static/vis-timeline-graph2d.min.css
iqm/pulse/playlist/visualisation/templates/static/vis-timeline-graph2d.min.js
iqm_pulse-12.7.3.dist-info/LICENSE.txt
iqm_pulse-12.7.3.dist-info/METADATA
iqm_pulse-12.7.3.dist-info/WHEEL
iqm_pulse-12.7.3.dist-info/top_level.txt
iqm_pulse-12.7.3.dist-info/RECORD
