Metadata-Version: 2.1
Name: iqm-pulse
Version: 12.7.3
Summary: A Python-based project for providing interface and implementations for control pulses.
Author-email: IQM Finland Oy <info@meetiqm.com>
License: Apache License
Project-URL: Documentation, https://docs.meetiqm.com/iqm-pulse/
Project-URL: Homepage, https://pypi.org/project/iqm-pulse/
Classifier: Development Status :: 4 - Beta
Classifier: Programming Language :: Python :: 3 :: Only
Classifier: Topic :: Scientific/Engineering :: Physics
Classifier: Intended Audience :: Science/Research
Requires-Python: >=3.11
License-File: LICENSE.txt
Requires-Dist: iqm-data-definitions <3.0,>=2.18
Requires-Dist: python-rapidjson ==1.20
Requires-Dist: jinja2 ==3.0.3
Requires-Dist: numpy <3.0,>=1.26.4
Requires-Dist: scipy <1.16,>=1.11.4
Requires-Dist: scipy-stubs
